quokka_flask_htmlbuilder-0.12-py2.7-nspkg.pth
flaskext/htmlbuilder.py
quokka_flask_htmlbuilder-0.12.dist-info/DESCRIPTION.rst
quokka_flask_htmlbuilder-0.12.dist-info/METADATA
quokka_flask_htmlbuilder-0.12.dist-info/RECORD
quokka_flask_htmlbuilder-0.12.dist-info/WHEEL
quokka_flask_htmlbuilder-0.12.dist-info/metadata.json
quokka_flask_htmlbuilder-0.12.dist-info/namespace_packages.txt
quokka_flask_htmlbuilder-0.12.dist-info/top_level.txt
