Metadata-Version: 2.0
Name: quokka-flask-htmlbuilder
Version: 0.12
Summary: Fork of Flexible Python-only HTML generation for Flask
Home-page: http://github.com/quokkaproject/flask-htmlbuilder
Author: QuokkaProject
Author-email: zarchaoz@gmail.com
License: MIT
Platform: any
Classifier: Development Status :: 4 - Beta
Classifier: Environment :: Web Environment
Classifier: Intended Audience :: Developers
Classifier: License :: OSI Approved :: MIT License
Classifier: Operating System :: OS Independent
Classifier: Programming Language :: Python
Classifier: Topic :: Internet :: WWW/HTTP :: Dynamic Content
Classifier: Topic :: Software Development :: Libraries :: Python Modules
Requires-Dist: Flask
